{"name":"Danh Môn Kiều Thê","folder":"danhmonkieuthe","tacGia":"Cửu Lam","theLoai":"Ngôn Tình","trangThai":"Full","description":"Văn án: Trong mắt mọi người, Vệ Tam công tử kinh tài tuyệt diễm* giống như hoa sen trong nước, chỉ có thể đứng nhìn từ xa chứ tuyệt đối không thể khinh nhờn.<br><br>Ban đầu Lạc Bảo Anh cũng nghĩ như vậy, ai ngờ sau khi trở thành tiểu biểu muội của chàng thì mới phát hiện…<br><br>Tất cả những điều này cần phải xem xét lại!<br><br>Tóm tắt cơ bản: Chuyện xưa kể về một quý nữ Đông Sơn tái khởi*, từng bước bồi đắp thanh danh sau đó gả vào danh môn vọng tộc.<br><br>(*) Kinh tài tuyệt diễm: Tài năng và sắc đẹp khiến người khác phải kinh ngạc, hoảng sợ.<br><br>(*) Đông Sơn tái khởi: chờ đợi thời cơ để trở lại."}