{"name":"Ngắm Bắn Trúng Tim Anh","folder":"ngambantrungtimanh","tacGia":"Triệu Thừa Dư","theLoai":"Ngôn Tình","trangThai":"Đang ra","description":"Tên gốc: 八倍镜瞄准，击中你心脏<br><br>Tác giả: 赵承妤<br><br>Edit: Nhóm Cà phê Muối<br><br>Giới thiệu:<br><br>Gặp mặt nhau là một sự tình cờ, Nhiễm Nhị đi tới đây cũng không ngờ được là cô sẽ bị sung công để biểu diễn một bản độc tấu trân sân khấu.<br><br>Lâm Trạm là một đặc công ưu tú, điển trai, thanh lãnh, trầm tĩnh, chỉ quan tâm tới công việc, lần đầu tiên, ánh mắt anh rơi xuống một cô gái, và còn rất lâu, rất lâu không dời đi…"}